aiohttp_auth/__init__.py
aiohttp_auth/permissions.py
aiohttp_auth/acl/__init__.py
aiohttp_auth/acl/abc.py
aiohttp_auth/acl/acl.py
aiohttp_auth/acl/decorators.py
aiohttp_auth/auth/__init__.py
aiohttp_auth/auth/abstract_auth.py
aiohttp_auth/auth/auth.py
aiohttp_auth/auth/cookie_ticket_auth.py
aiohttp_auth/auth/decorators.py
aiohttp_auth/auth/session_ticket_auth.py
aiohttp_auth/auth/ticket_auth.py
aiohttp_auth/autz/__init__.py
aiohttp_auth/autz/abc.py
aiohttp_auth/autz/autz.py
aiohttp_auth/autz/decorators.py
aiohttp_auth/autz/policy/__init__.py
aiohttp_auth/autz/policy/acl.py
aiohttp_auth_autz-0.2.2.dist-info/DESCRIPTION.rst
aiohttp_auth_autz-0.2.2.dist-info/METADATA
aiohttp_auth_autz-0.2.2.dist-info/RECORD
aiohttp_auth_autz-0.2.2.dist-info/WHEEL
aiohttp_auth_autz-0.2.2.dist-info/metadata.json
aiohttp_auth_autz-0.2.2.dist-info/top_level.txt
