Metadata-Version: 2.0
Name: aiohttp-auth-autz
Version: 0.2.2
Summary: Authorization and authentication middleware plugin for aiohttp.
Home-page: https://github.com/ilex/aiohttp_auth_autz
Author: ilex (fork author)
Author-email: gnarlychicken@gmx.com
License: MIT
Platform: UNKNOWN
Classifier: Development Status :: 3 - Alpha
Classifier: Intended Audience :: Developers
Classifier: Topic :: Internet :: WWW/HTTP :: Session
Classifier: License :: OSI Approved :: MIT License
Classifier: Programming Language :: Python :: 3 :: Only
Classifier: Programming Language :: Python :: 3.5
Classifier: Programming Language :: Python :: 3.6
Requires-Dist: aiohttp (>=2.0.7)
Requires-Dist: ticket-auth (==0.1.4)
